madnis/__init__.py
madnis/integrator/__init__.py
madnis/integrator/buffer.py
madnis/integrator/channel_grouping.py
madnis/integrator/integrand.py
madnis/integrator/integrator.py
madnis/integrator/losses.py
madnis/integrator/metrics.py
madnis/integrator/vegas_pretraining.py
madnis/nn/__init__.py
madnis/nn/discrete_made.py
madnis/nn/discrete_transformer.py
madnis/nn/flow.py
madnis/nn/masked_mlp.py
madnis/nn/mixed_flow.py
madnis/nn/mlp.py
madnis/nn/splines.py
madnis-0.2.2.dist-info/licenses/LICENSE
madnis-0.2.2.dist-info/METADATA
madnis-0.2.2.dist-info/WHEEL
madnis-0.2.2.dist-info/top_level.txt
madnis-0.2.2.dist-info/RECORD
