Metadata-Version: 2.4
Name: madnis
Version: 0.2.2
Summary: Library for neural importance sampling
Author-email: Ramon Winterhalder <ramon.winterhalder@unimi.it>, Theo Heimel <theo.heimel@uclouvain.be>
Project-URL: Homepage, https://github.com/madgraph-ml/madnis
Project-URL: Issues, https://github.com/madgraph-ml/madnis/issues
Classifier: Programming Language :: Python :: 3
Classifier: License :: OSI Approved :: MIT License
Classifier: Operating System :: OS Independent
Requires-Python: >=3.10
License-File: LICENSE
Requires-Dist: numpy
Requires-Dist: torch
Requires-Dist: torchtestcase
Provides-Extra: vegas
Requires-Dist: vegas; extra == "vegas"
Dynamic: license-file
